MANIFEST.in
README.rst
pyproject.toml
setup.cfg
setup.py
docs/info.txt
maetl_population.egg-info/PKG-INFO
maetl_population.egg-info/SOURCES.txt
maetl_population.egg-info/dependency_links.txt
maetl_population.egg-info/requires.txt
maetl_population.egg-info/top_level.txt
population/__init__.py
population/admin.py
population/apps.py
population/forms.py
population/models.py
population/serializers.py
population/tests.py
population/urls.py
population/utils.py
population/views.py
population/migrations/0001_initial.py
population/migrations/__init__.py
population/templates/population/dashboard.html
population/templates/population/sidebar.html
population/templates/population/custom/administrativepost/administrativepost_input.html
population/templates/population/custom/administrativepost/administrativepost_list.html
population/templates/population/custom/aldeia/aldeia_input.html
population/templates/population/custom/aldeia/aldeia_list.html
population/templates/population/custom/citizen/citizen_input.html
population/templates/population/custom/citizen/citizen_list.html
population/templates/population/custom/familyposition/familyposition_input.html
population/templates/population/custom/familyposition/familyposition_list.html
population/templates/population/custom/level_education/level_education_input.html
population/templates/population/custom/level_education/level_education_list.html
population/templates/population/custom/municipality/municipality_input.html
population/templates/population/custom/municipality/municipality_list.html
population/templates/population/custom/profession/profession_input.html
population/templates/population/custom/profession/profession_list.html
population/templates/population/custom/religion/religion_input.html
population/templates/population/custom/religion/religion_list.html
population/templates/population/custom/village/village_input.html
population/templates/population/custom/village/village_list.html
population/templates/population/familycard_online/familycard_list.html
population/templates/population/familycard_online/newpasswordfamilycard.html
population/templates/population/familycard_online/registerfamilycard.html
